reddit_mcp_server/__init__.py
reddit_mcp_server/chrome_client.py
reddit_mcp_server/py.typed
reddit_mcp_server/reddit_client.py
reddit_mcp_server/server.py
reddit_mcp_server/tools/__init__.py
reddit_mcp_server/tools/advanced_tools.py
reddit_mcp_server/tools/best_communities_tools.py
reddit_mcp_server/tools/comment_tools.py
reddit_mcp_server/tools/content_tools.py
reddit_mcp_server/tools/reddit_instance_tools.py
reddit_mcp_server/tools/subreddit_tools.py
reddit_mcp_server/tools/user_tools.py
reddit_mcp_server/utils/__init__.py
reddit_mcp_server/utils/export.py
reddit_mcp_server-1.2.0.dist-info/licenses/LICENSE
reddit_mcp_server-1.2.0.dist-info/METADATA
reddit_mcp_server-1.2.0.dist-info/WHEEL
reddit_mcp_server-1.2.0.dist-info/entry_points.txt
reddit_mcp_server-1.2.0.dist-info/top_level.txt
reddit_mcp_server-1.2.0.dist-info/RECORD
