Metadata-Version: 2.4
Name: reddit-mcp-server
Version: 1.2.0
Summary: Comprehensive Reddit research MCP server using PRAW
Author-email: Reddit MCP Server Contributors <reddit-mcp@users.noreply.github.com>
License: MIT
Project-URL: Homepage, https://github.com/reddit-mcp/reddit-mcp-server
Project-URL: Repository, https://github.com/reddit-mcp/reddit-mcp-server
Project-URL: Issues, https://github.com/reddit-mcp/reddit-mcp-server/issues
Classifier: Development Status :: 4 - Beta
Classifier: Intended Audience :: Developers
Classifier: License :: OSI Approved :: MIT License
Classifier: Programming Language :: Python :: 3
Classifier: Programming Language :: Python :: 3.8
Classifier: Programming Language :: Python :: 3.9
Classifier: Programming Language :: Python :: 3.10
Classifier: Programming Language :: Python :: 3.11
Classifier: Programming Language :: Python :: 3.12
Requires-Python: >=3.8
License-File: LICENSE
Requires-Dist: mcp>=1.0.0
Requires-Dist: praw>=7.7.1
Requires-Dist: python-dotenv>=1.0.0
Requires-Dist: aiohttp>=3.8.0
Requires-Dist: typing-extensions>=4.0.0
Requires-Dist: undetected-chromedriver>=3.5.0
Requires-Dist: selenium>=4.15.0
Requires-Dist: beautifulsoup4>=4.12.0
Provides-Extra: dev
Requires-Dist: pytest>=7.0.0; extra == "dev"
Requires-Dist: pytest-asyncio>=0.21.0; extra == "dev"
Requires-Dist: black>=23.0.0; extra == "dev"
Requires-Dist: isort>=5.12.0; extra == "dev"
Requires-Dist: mypy>=1.0.0; extra == "dev"
Requires-Dist: ruff>=0.1.0; extra == "dev"
Dynamic: license-file
